py_missing_releases_librmo/__init__.py
py_missing_releases_librmo/_database.py
py_missing_releases_librmo/_utils.py
py_missing_releases_librmo/missing_releases.py
py_missing_releases_librmo-0.1.1.dist-info/METADATA
py_missing_releases_librmo-0.1.1.dist-info/WHEEL
py_missing_releases_librmo-0.1.1.dist-info/licenses/LICENSE
py_missing_releases_librmo-0.1.1.dist-info/RECORD
