Metadata-Version: 2.3
Name: py_missing_releases_librmo
Version: 0.1.1
Summary: Uses information stored in librmo to discover missing album releases from your music artists
Author: Samuel Shiels
License-File: LICENSE
Classifier: Development Status :: 3 - Alpha
Classifier: Environment :: Other Environment
Classifier: Intended Audience :: Developers
Classifier: Intended Audience :: System Administrators
Classifier: License :: OSI Approved :: MIT License
Classifier: Operating System :: POSIX :: Linux
Classifier: Programming Language :: Python :: 3
Classifier: Topic :: Utilities
Requires-Python: >=3.11.5
Requires-Dist: music-brainz-api-micro
